country_db/__init__.py
country_db/core.py
country_db/data/country.json
tests/__init__.py
tests/test_country_db.py
country_db-1.0.dist-info/LICENSE
country_db-1.0.dist-info/METADATA
country_db-1.0.dist-info/WHEEL
country_db-1.0.dist-info/top_level.txt
country_db-1.0.dist-info/RECORD
