Metadata-Version: 2.1
Name: country-db
Version: 1.0
Home-page: https://github.com/sivakumar-mahalingam/country-db/
Author: ['Sivakumar Mahalingam', 'Sabarinath Velayudham']
Project-URL: Source, https://github.com/sivakumar-mahalingam/country-db
Project-URL: Tracker, https://github.com/sivakumar-mahalingam/country-db/issues
Keywords: country
Classifier: License :: OSI Approved :: MIT License
Classifier: Development Status :: 5 - Production/Stable
Classifier: Intended Audience :: Developers
Classifier: Intended Audience :: Information Technology
Classifier: Natural Language :: English
Classifier: Operating System :: OS Independent
Classifier: Typing :: Typed
Requires-Python: >=3.8
License-File: LICENSE
